edc_fabric/__init__.py
edc_fabric/fabfile/__init__.py
edc_fabric/fabfile/apache.py
edc_fabric/fabfile/conf.py
edc_fabric/fabfile/constants.py
edc_fabric/fabfile/prompts.py
edc_fabric/fabfile/repositories.py
edc_fabric/fabfile/utils.py
edc_fabric/fabfile/brew/__init__.py
edc_fabric/fabfile/brew/tasks.py
edc_fabric/fabfile/deployment_host/__init__.py
edc_fabric/fabfile/deployment_host/deploy.py
edc_fabric/fabfile/environment/__init__.py
edc_fabric/fabfile/environment/tasks.py
edc_fabric/fabfile/files/__init__.py
edc_fabric/fabfile/files/dmg.py
edc_fabric/fabfile/files/utils.py
edc_fabric/fabfile/git/__init__.py
edc_fabric/fabfile/git/task.py
edc_fabric/fabfile/gunicorn/__init__.py
edc_fabric/fabfile/gunicorn/tasks.py
edc_fabric/fabfile/mysql/__init__.py
edc_fabric/fabfile/mysql/tasks.py
edc_fabric/fabfile/nginx/__init__.py
edc_fabric/fabfile/nginx/tasks.py
edc_fabric/fabfile/pip/__init__.py
edc_fabric/fabfile/pip/tasks.py
edc_fabric/fabfile/python/__init__.py
edc_fabric/fabfile/python/tasks.py
edc_fabric/fabfile/virtualenv/__init__.py
edc_fabric/fabfile/virtualenv/tasks.py
edc_fabric-0.1.5a1.dist-info/METADATA
edc_fabric-0.1.5a1.dist-info/RECORD
edc_fabric-0.1.5a1.dist-info/WHEEL
edc_fabric-0.1.5a1.dist-info/top_level.txt
